Workbook

Sheet Log
A8: Supplementary data - Model Inputs
A12: This dataset is supplementary data of modelling input assumptions for the following journal publication in Energy Conversion and Management
A14: Title: Modeling the diffusion of hydrogen-based steel and basic chemical production in Europe - A site specific approach.
A15: Authors: Marius Neuwirth*, Tobias Fleiter, René Hofmann
A17: *Affiliation: Modelling and provided data established at Fraunhofer Institute for Systems- and Innovation Research (ISI), Breslauer Str. 48, 76139 Karlsruhe
A19: Dataset version: 1.0
A21: This supplementary data contains assumptions and input data for the modelling approach. Data for the several scenarios are provided as well as technology-specific techno-economic parameter. This supplementary data is structured as follows:
A24: Scenario specific input data:
A25: 0. Sensitivity definitions: | C25: Hydrogen prices are named as 1, 2, 3, 4 reflecting on the 4 conducted hydrogen price sensitivities
C26: 1 | D26: high | E26: 2 | F26: medium-high | G26: 3 | H26: medium-low | I26: 4 | J26: low
C28: CO2 prices are named as 250, 300, 350, 400 reflecting on the 4 conducted CO2 price sensitivities according to their end prices in 2050
C29: 250 | D29: low | E29: 300 | F29: medium-low | G29: 350 | H29: medium-high | I29: 400 | J29: high
A31: Scenario specific input data:
A32: 1. Yearly energy carrier cost per country | H32: comment: | I32: energy carrier prices differ per country, except hydrogen prices (due to sensitivities)
A33: 2. Yearly energy carrier subsidies per country | H33: comment: | I33: no subsidies in any sensitivity
A34: 3. Yearly energy carrier taxes per country | H34: comment: | I34: no taxes in any sensitivity
A35: 4. Yearly energy carrier availability per country | H35: comment: | I35: unlimited availabilities in all sensitivities
A36: 5. Energy carrier emission factors | H36: comment: | I36: same energy carrier emission facotrs in all sensitivities
A37: 6. Investment funding | H37: comment: | I37: no funding in any sensitivity
A38: 7. Yearly CO2-price assumption | H38: comment: | I38: CO2 prices don´t differ per country, but per sensitivitiy
A39: 8. Hydrogen sensitivity prices | H39: comment: | I39: H2 prices don´t differ per country, but per sensitivitiy
A41: Technology-specific techno-economic parameter
A42: 1. Capital investment costs per technology | H42: comment: | I42: same CAPEX in all sensitivities
A43: 2. Fixed operational costs per technology | H43: comment: | I43: same OPEX in all sensitivities
A44: 3. Specific energy, steam and feedstock consumption (SEC) per technology | H44: comment: | I44: same SEC´s in all sensitivities
A45: 4. Energy carrier shares on energy consumption per technology | H45: comment: | I45: same energy carrier shares in all sensitivities
A46: 5. Energy carrier shares on steam consumption per technology | H46: comment: | I46: same energy carrier shares in all sensitivities
A47: 6. Energy carrier shares on feedstock consumption per technology | H47: comment: | I47: same energy carrier shares in all sensitivities
A48: 7. Theoretical lifetime per technology | H48: comment: | I48: same technology lifetime assumptions in all sensitivities
A49: 8. Assumptions on efficiency improvements per technology | H49: comment: | I49: no efficiency improvements in all sensitivities
A51: Contact: Marius.Neuwirth@isi.fraunhofer.de
A52: For Feedback or questions regarding the supplementary material, methodological approach of modelling or linked journal publication please don´t hesitate to send an e-mail!

Sheet sensitivity_definition
A1: id_scenario | B1: CO2 price path | C1: sensitivity_name | D1: scenario_description
A2: 1 | B2: 80 -> 250 | C2: 1_250 | D2: This sensitivity reflects on the combination of high hydrogen price path and low CO2 price path
A3: 1 | B3: 80 -> 300 | C3: 1_300 | D3: This sensitivity reflects on the combination of high hydrogen price path and medium-low CO2 price path
A4: 1 | B4: 80 -> 350 | C4: 1_350 | D4: This sensitivity reflects on the combination of high hydrogen price path and medium-high CO2 price path
A5: 1 | B5: 80 -> 400 | C5: 1_400 | D5: This sensitivity reflects on the combination of high hydrogen price path and high CO2 price path
A6: 2 | B6: 80 -> 250 | C6: 2_250 | D6: This sensitivity reflects on the combination of medium-high hydrogen price path and low CO2 price path
A7: 2 | B7: 80 -> 300 | C7: 2_300 | D7: This sensitivity reflects on the combination of medium-high hydrogen price path and medium-low CO2 price path
A8: 2 | B8: 80 -> 350 | C8: 2_350 | D8: This sensitivity reflects on the combination of medium-high hydrogen price path and medium-high CO2 price path
A9: 2 | B9: 80 -> 400 | C9: 2_400 | D9: This sensitivity reflects on the combination of medium-high hydrogen price path and high CO2 price path
A10: 3 | B10: 80 -> 250 | C10: 3_250 | D10: This sensitivity reflects on the combination of medium-low hydrogen price path and low CO2 price path
A11: 3 | B11: 80 -> 300 | C11: 3_300 | D11: This sensitivity reflects on the combination of medium-low hydrogen price path and medium-low CO2 price path
A12: 3 | B12: 80 -> 350 | C12: 3_350 | D12: This sensitivity reflects on the combination of medium-low hydrogen price path and medium-high CO2 price path
A13: 3 | B13: 80 -> 400 | C13: 3_400 | D13: This sensitivity reflects on the combination of medium-low hydrogen price path and high CO2 price path
... A17: 4 | B17: 80 -> 400 | C17: 4_400 | D17: This sensitivity reflects on the combination of low hydrogen price path and high CO2 price path

Sheet energy_carrier_cost
A1: id_scenario | B1: id_region | C1: id_energy_carrier | D1: cost_2022_in_euro_per_gj | E1: cost_2030_in_euro_per_gj | F1: cost_2050_in_euro_per_gj
A2: 1 | B2: 1 | C2: 1 | D2: 57.72 | E2: 37.72 | F2: 31.49
A3: 1 | B3: 1 | C3: 2 | D3: 24.95 | E3: 14.39 | F3: 13.69
A4: 1 | B4: 1 | C4: 3 | D4: 4.5 | E4: 3.3817056 | F4: 2.9387784
A5: 1 | B5: 1 | C5: 4 | D5: 21.41 | E5: 10.36 | F5: 8.29
A6: 1 | B6: 1 | C6: 5 | D6: 15.55 | E6: 7.53 | F6: 6.02
A7: 1 | B7: 1 | C7: 6 | D7: 15.55 | E7: 7.53 | F7: 6.02
A8: 1 | B8: 1 | C8: 7 | D8: 36.35 | E8: 11.08 | F8: 14.02
A9: 1 | B9: 1 | C9: 8 | D9: 0 | E9: 0 | F9: 0
A10: 1 | B10: 1 | C10: 9 | D10: 0 | E10: 0 | F10: 0
A11: 1 | B11: 1 | C11: 10 | D11: 0 | E11: 0 | F11: 0
A12: 1 | B12: 1 | C12: 11 | D12: 18.19 | E12: 8.8 | F12: 7.04
A13: 1 | B13: 1 | C13: 13 | D13: 36.35 | E13: 11.08 | F13: 14.02
... A4951: 10 | B4951: 34 | C4951: 16 | D4951: 54.23 | E4951: 28.36 | F4951: 18.41

Sheet energy_carrier_subsidies
A1: id_scenario | B1: id_region | C1: region_name | D1: id_energy_carrier | E1: energy_carrier_name | F1: subsidies_2022_in_euro_per_gj | G1: subsidies_2030_in_euro_per_gj | H1: subsidies_2050_in_euro_per_gj | I1: comment
A2: 1 | B2: 1 | C2: =VLOOKUP(B2,id_region!$A$1:$C$35,2,0) -> Austria | D2: 1 | E2: =VLOOKUP(D2,id_energy_carrier!$A$1:$C$26,2,0) -> Electricity | F2: 0 | G2: 0 | H2: 0 | I2: no subsidies
A3: 1 | B3: 2 | C3: =VLOOKUP(B3,id_region!$A$1:$C$35,2,0) -> Belgium | D3: 1 | E3: =VLOOKUP(D3,id_energy_carrier!$A$1:$C$26,2,0) -> Electricity | F3: 0 | G3: 0 | H3: 0 | I3: no subsidies
A4: 1 | B4: 3 | C4: =VLOOKUP(B4,id_region!$A$1:$C$35,2,0) -> Cyprus | D4: 1 | E4: =VLOOKUP(D4,id_energy_carrier!$A$1:$C$26,2,0) -> Electricity | F4: 0 | G4: 0 | H4: 0 | I4: no subsidies
A5: 1 | B5: 4 | C5: =VLOOKUP(B5,id_region!$A$1:$C$35,2,0) -> Czech_Republic | D5: 1 | E5: =VLOOKUP(D5,id_energy_carrier!$A$1:$C$26,2,0) -> Electricity | F5: 0 | G5: 0 | H5: 0 | I5: no subsidies
A6: 1 | B6: 5 | C6: =VLOOKUP(B6,id_region!$A$1:$C$35,2,0) -> Denmark | D6: 1 | E6: =VLOOKUP(D6,id_energy_carrier!$A$1:$C$26,2,0) -> Electricity | F6: 0 | G6: 0 | H6: 0 | I6: no subsidies
A7: 1 | B7: 6 | C7: =VLOOKUP(B7,id_region!$A$1:$C$35,2,0) -> Estonia | D7: 1 | E7: =VLOOKUP(D7,id_energy_carrier!$A$1:$C$26,2,0) -> Electricity | F7: 0 | G7: 0 | H7: 0 | I7: no subsidies
A8: 1 | B8: 7 | C8: =VLOOKUP(B8,id_region!$A$1:$C$35,2,0) -> Finland | D8: 1 | E8: =VLOOKUP(D8,id_energy_carrier!$A$1:$C$26,2,0) -> Electricity | F8: 0 | G8: 0 | H8: 0 | I8: no subsidies
A9: 1 | B9: 8 | C9: =VLOOKUP(B9,id_region!$A$1:$C$35,2,0) -> France | D9: 1 | E9: =VLOOKUP(D9,id_energy_carrier!$A$1:$C$26,2,0) -> Electricity | F9: 0 | G9: 0 | H9: 0 | I9: no subsidies
A10: 1 | B10: 9 | C10: =VLOOKUP(B10,id_region!$A$1:$C$35,2,0) -> Germany | D10: 1 | E10: =VLOOKUP(D10,id_energy_carrier!$A$1:$C$26,2,0) -> Electricity | F10: 0 | G10: 0 | H10: 0 | I10: no subsidies
A11: 1 | B11: 10 | C11: =VLOOKUP(B11,id_region!$A$1:$C$35,2,0) -> Greece | D11: 1 | E11: =VLOOKUP(D11,id_energy_carrier!$A$1:$C$26,2,0) -> Electricity | F11: 0 | G11: 0 | H11: 0 | I11: no subsidies
A12: 1 | B12: 11 | C12: =VLOOKUP(B12,id_region!$A$1:$C$35,2,0) -> Hungary | D12: 1 | E12: =VLOOKUP(D12,id_energy_carrier!$A$1:$C$26,2,0) -> Electricity | F12: 0 | G12: 0 | H12: 0 | I12: no subsidies
A13: 1 | B13: 12 | C13: =VLOOKUP(B13,id_region!$A$1:$C$35,2,0) -> Ireland | D13: 1 | E13: =VLOOKUP(D13,id_energy_carrier!$A$1:$C$26,2,0) -> Electricity | F13: 0 | G13: 0 | H13: 0 | I13: no subsidies
... A2041: 4 | B2041: 34 | C2041: =VLOOKUP(B2041,id_region!$A$1:$C$35,2,0) -> Serbia | D2041: 16 | E2041: =VLOOKUP(D2041,id_energy_carrier!$A$1:$C$26,2,0) -> #N/A | F2041: 0 | G2041: 0 | H2041: 0 | I2041: no subsidies

Sheet energy_carrier_taxes
A1: id_scenario | B1: id_region | C1: region_name | D1: id_energy_carrier | E1: energy_carrier_name | F1: taxes_2022_in_euro_per_gj | G1: taxes_2030_in_euro_per_gj | H1: taxes_2050_in_euro_per_gj | I1: comment
A2: 1 | B2: 1 | C2: =VLOOKUP(B2,id_region!$A$1:$C$35,2,0) -> Austria | D2: 1 | E2: =VLOOKUP(D2,id_energy_carrier!$A$1:$C$26,2,0) -> Electricity | F2: 0 | G2: 0 | H2: 0 | I2: no taxes
A3: 1 | B3: 1 | C3: =VLOOKUP(B3,id_region!$A$1:$C$35,2,0) -> Austria | D3: 2 | E3: =VLOOKUP(D3,id_energy_carrier!$A$1:$C$26,2,0) -> #N/A | F3: 0 | G3: 0 | H3: 0 | I3: no taxes
A4: 1 | B4: 1 | C4: =VLOOKUP(B4,id_region!$A$1:$C$35,2,0) -> Austria | D4: 3 | E4: =VLOOKUP(D4,id_energy_carrier!$A$1:$C$26,2,0) -> Coal | F4: 0 | G4: 0 | H4: 0 | I4: no taxes
A5: 1 | B5: 1 | C5: =VLOOKUP(B5,id_region!$A$1:$C$35,2,0) -> Austria | D5: 4 | E5: =VLOOKUP(D5,id_energy_carrier!$A$1:$C$26,2,0) -> Natural gas | F5: 0 | G5: 0 | H5: 0 | I5: no taxes
A6: 1 | B6: 1 | C6: =VLOOKUP(B6,id_region!$A$1:$C$35,2,0) -> Austria | D6: 5 | E6: =VLOOKUP(D6,id_energy_carrier!$A$1:$C$26,2,0) -> #N/A | F6: 0 | G6: 0 | H6: 0 | I6: no taxes
A7: 1 | B7: 1 | C7: =VLOOKUP(B7,id_region!$A$1:$C$35,2,0) -> Austria | D7: 6 | E7: =VLOOKUP(D7,id_energy_carrier!$A$1:$C$26,2,0) -> #N/A | F7: 0 | G7: 0 | H7: 0 | I7: no taxes
A8: 1 | B8: 1 | C8: =VLOOKUP(B8,id_region!$A$1:$C$35,2,0) -> Austria | D8: 7 | E8: =VLOOKUP(D8,id_energy_carrier!$A$1:$C$26,2,0) -> #N/A | F8: 0 | G8: 0 | H8: 0 | I8: no taxes
A9: 1 | B9: 1 | C9: =VLOOKUP(B9,id_region!$A$1:$C$35,2,0) -> Austria | D9: 8 | E9: =VLOOKUP(D9,id_energy_carrier!$A$1:$C$26,2,0) -> #N/A | F9: 0 | G9: 0 | H9: 0 | I9: no taxes
A10: 1 | B10: 1 | C10: =VLOOKUP(B10,id_region!$A$1:$C$35,2,0) -> Austria | D10: 9 | E10: =VLOOKUP(D10,id_energy_carrier!$A$1:$C$26,2,0) -> #N/A | F10: 0 | G10: 0 | H10: 0 | I10: no taxes
A11: 1 | B11: 1 | C11: =VLOOKUP(B11,id_region!$A$1:$C$35,2,0) -> Austria | D11: 10 | E11: =VLOOKUP(D11,id_energy_carrier!$A$1:$C$26,2,0) -> #N/A | F11: 0 | G11: 0 | H11: 0 | I11: no taxes
A12: 1 | B12: 1 | C12: =VLOOKUP(B12,id_region!$A$1:$C$35,2,0) -> Austria | D12: 13 | E12: =VLOOKUP(D12,id_energy_carrier!$A$1:$C$26,2,0) -> #N/A | F12: 0 | G12: 0 | H12: 0 | I12: no taxes
A13: 1 | B13: 1 | C13: =VLOOKUP(B13,id_region!$A$1:$C$35,2,0) -> Austria | D13: 14 | E13: =VLOOKUP(D13,id_energy_carrier!$A$1:$C$26,2,0) -> Naphtha | F13: 0 | G13: 0 | H13: 0 | I13: no taxes
... A2041: 4 | B2041: 34 | C2041: =VLOOKUP(B2041,id_region!$A$1:$C$35,2,0) -> Serbia | D2041: 11 | E2041: =VLOOKUP(D2041,id_energy_carrier!$A$1:$C$26,2,0) -> Derived Gases | F2041: 0 | G2041: 0 | H2041: 0 | I2041: no taxes

Sheet energy_carrier_availability
A1: id_scenario | B1: id_region | C1: region_name | D1: id_energy_carrier | E1: energy_carrier_name | F1: unit | G1: availability_2022_in_gj | H1: availability_2030_in_gj | I1: availability_2050_in_gj | J1: comment
A2: 1 | B2: 1 | C2: =VLOOKUP(B2,id_region!$A$1:$C$35,2,0) -> Austria | D2: 1 | E2: Electricity | F2: GJ | G2: unlimited | H2: unlimited | I2: unlimited | J2: Assumption, represents "no constraints"
A3: 1 | B3: 1 | C3: =VLOOKUP(B3,id_region!$A$1:$C$35,2,0) -> Austria | D3: 2 | E3: Fuel oil | F3: GJ | G3: unlimited | H3: unlimited | I3: unlimited | J3: Assumption, represents "no constraints"
A4: 1 | B4: 1 | C4: =VLOOKUP(B4,id_region!$A$1:$C$35,2,0) -> Austria | D4: 3 | E4: Coal | F4: GJ | G4: unlimited | H4: unlimited | I4: unlimited | J4: Assumption, represents "no constraints"
A5: 1 | B5: 1 | C5: =VLOOKUP(B5,id_region!$A$1:$C$35,2,0) -> Austria | D5: 4 | E5: Natural gas | F5: GJ | G5: unlimited | H5: unlimited | I5: unlimited | J5: Assumption, represents "no constraints"
A6: 1 | B6: 1 | C6: =VLOOKUP(B6,id_region!$A$1:$C$35,2,0) -> Austria | D6: 5 | E6: Other fossil | F6: GJ | G6: unlimited | H6: unlimited | I6: unlimited | J6: Assumption, represents "no constraints"
A7: 1 | B7: 1 | C7: =VLOOKUP(B7,id_region!$A$1:$C$35,2,0) -> Austria | D7: 6 | E7: Waste non-RES | F7: GJ | G7: unlimited | H7: unlimited | I7: unlimited | J7: Assumption, represents "no constraints"
A8: 1 | B8: 1 | C8: =VLOOKUP(B8,id_region!$A$1:$C$35,2,0) -> Austria | D8: 7 | E8: Biomass | F8: GJ | G8: unlimited | H8: unlimited | I8: unlimited | J8: Assumption, represents "no constraints"
A9: 1 | B9: 1 | C9: =VLOOKUP(B9,id_region!$A$1:$C$35,2,0) -> Austria | D9: 8 | E9: District heating | F9: GJ | G9: unlimited | H9: unlimited | I9: unlimited | J9: Assumption, represents "no constraints"
A10: 1 | B10: 1 | C10: =VLOOKUP(B10,id_region!$A$1:$C$35,2,0) -> Austria | D10: 9 | E10: Solar energy | F10: GJ | G10: unlimited | H10: unlimited | I10: unlimited | J10: Assumption, represents "no constraints"
A11: 1 | B11: 1 | C11: =VLOOKUP(B11,id_region!$A$1:$C$35,2,0) -> Austria | D11: 10 | E11: Ambient heat | F11: GJ | G11: unlimited | H11: unlimited | I11: unlimited | J11: Assumption, represents "no constraints"
A12: 1 | B12: 1 | C12: =VLOOKUP(B12,id_region!$A$1:$C$35,2,0) -> Austria | D12: 13 | E12: Other RES | F12: GJ | G12: unlimited | H12: unlimited | I12: unlimited | J12: Assumption, represents "no constraints"
A13: 1 | B13: 1 | C13: =VLOOKUP(B13,id_region!$A$1:$C$35,2,0) -> Austria | D13: 14 | E13: Naphtha | F13: GJ | G13: unlimited | H13: unlimited | I13: unlimited | J13: Assumption, represents "no constraints"
... A2041: 4 | B2041: 34 | C2041: =VLOOKUP(B2041,id_region!$A$1:$C$35,2,0) -> Serbia | D2041: 11 | E2041: Ambient heat | F2041: GJ | G2041: unlimited | H2041: unlimited | I2041: unlimited | J2041: Assumption, represents "no constraints"

Sheet energy_carrier_emission_factors
A1: id_scenario | B1: id_region | C1: region_name | D1: id_energy_carrier | E1: energy_carrier_name | F1: emission_2015_in_ton_per_gj | G1: emission_2050_in_ton_per_gj
A2: 1 | B2: 1 | C2: =VLOOKUP(B2,id_region!$A$1:$C$35,2,0) -> Austria | D2: 1 | E2: =VLOOKUP(D2,id_energy_carrier!$A$1:$C$26,2,0) -> Electricity | F2: 0 | G2: 0
A3: 1 | B3: 1 | C3: =VLOOKUP(B3,id_region!$A$1:$C$35,2,0) -> Austria | D3: 3 | E3: =VLOOKUP(D3,id_energy_carrier!$A$1:$C$26,2,0) -> Coal | F3: 0.096 | G3: 0.096
A4: 1 | B4: 1 | C4: =VLOOKUP(B4,id_region!$A$1:$C$35,2,0) -> Austria | D4: 4 | E4: =VLOOKUP(D4,id_energy_carrier!$A$1:$C$26,2,0) -> Natural gas | F4: 0.056 | G4: 0.056
A5: 1 | B5: 1 | C5: =VLOOKUP(B5,id_region!$A$1:$C$35,2,0) -> Austria | D5: 14 | E5: =VLOOKUP(D5,id_energy_carrier!$A$1:$C$26,2,0) -> Naphtha | F5: 0.076 | G5: 0.076
A6: 1 | B6: 1 | C6: =VLOOKUP(B6,id_region!$A$1:$C$35,2,0) -> Austria | D6: 15 | E6: =VLOOKUP(D6,id_energy_carrier!$A$1:$C$26,2,0) -> Hydrogen | F6: 0 | G6: 0
A7: 1 | B7: 1 | C7: =VLOOKUP(B7,id_region!$A$1:$C$35,2,0) -> Austria | D7: 11 | E7: =VLOOKUP(D7,id_energy_carrier!$A$1:$C$26,2,0) -> Derived Gases | F7: 0 | G7: 0
A8: 1 | B8: 2 | C8: =VLOOKUP(B8,id_region!$A$1:$C$35,2,0) -> Belgium | D8: 1 | E8: =VLOOKUP(D8,id_energy_carrier!$A$1:$C$26,2,0) -> Electricity | F8: 0 | G8: 0
A9: 1 | B9: 2 | C9: =VLOOKUP(B9,id_region!$A$1:$C$35,2,0) -> Belgium | D9: 3 | E9: =VLOOKUP(D9,id_energy_carrier!$A$1:$C$26,2,0) -> Coal | F9: 0.096 | G9: 0.096
A10: 1 | B10: 2 | C10: =VLOOKUP(B10,id_region!$A$1:$C$35,2,0) -> Belgium | D10: 4 | E10: =VLOOKUP(D10,id_energy_carrier!$A$1:$C$26,2,0) -> Natural gas | F10: 0.056 | G10: 0.056
A11: 1 | B11: 2 | C11: =VLOOKUP(B11,id_region!$A$1:$C$35,2,0) -> Belgium | D11: 14 | E11: =VLOOKUP(D11,id_energy_carrier!$A$1:$C$26,2,0) -> Naphtha | F11: 0 | G11: 0
A12: 1 | B12: 2 | C12: =VLOOKUP(B12,id_region!$A$1:$C$35,2,0) -> Belgium | D12: 15 | E12: =VLOOKUP(D12,id_energy_carrier!$A$1:$C$26,2,0) -> Hydrogen | F12: 0 | G12: 0
A13: 1 | B13: 2 | C13: =VLOOKUP(B13,id_region!$A$1:$C$35,2,0) -> Belgium | D13: 11 | E13: =VLOOKUP(D13,id_energy_carrier!$A$1:$C$26,2,0) -> Derived Gases | F13: 0 | G13: 0
... A1014: 5 | B1014: 33 | C1014: =VLOOKUP(B1014,id_region!$A$1:$C$35,2,0) -> Iceland | D1014: 15 | E1014: =VLOOKUP(D1014,id_energy_carrier!$A$1:$C$26,2,0) -> Hydrogen | F1014: 0 | G1014: 0
A1015: 5 | B1015: 33 | C1015: =VLOOKUP(B1015,id_region!$A$1:$C$35,2,0) -> Iceland | D1015: 11 | F1015: 0 | G1015: 0
A1016: 5 | B1016: 34 | C1016: =VLOOKUP(B1016,id_region!$A$1:$C$35,2,0) -> Serbia | D1016: 1 | F1016: 0 | G1016: 0
A1017: 5 | B1017: 34 | C1017: =VLOOKUP(B1017,id_region!$A$1:$C$35,2,0) -> Serbia | D1017: 2 | F1017: 0.075 | G1017: 0.075
A1018: 5 | B1018: 34 | C1018: =VLOOKUP(B1018,id_region!$A$1:$C$35,2,0) -> Serbia | D1018: 3 | F1018: 0.096 | G1018: 0.096
A1019: 5 | B1019: 34 | C1019: =VLOOKUP(B1019,id_region!$A$1:$C$35,2,0) -> Serbia | D1019: 4 | F1019: 0.056 | G1019: 0.056
A1020: 5 | B1020: 34 | C1020: =VLOOKUP(B1020,id_region!$A$1:$C$35,2,0) -> Serbia | D1020: 5 | F1020: 0.84 | G1020: 0.84
A1021: 5 | B1021: 34 | C1021: =VLOOKUP(B1021,id_region!$A$1:$C$35,2,0) -> Serbia | D1021: 6 | F1021: 0.046 | G1021: 0.046
A1022: 5 | B1022: 34 | C1022: =VLOOKUP(B1022,id_region!$A$1:$C$35,2,0) -> Serbia | D1022: 7 | F1022: 0 | G1022: 0
A1023: 5 | B1023: 34 | C1023: =VLOOKUP(B1023,id_region!$A$1:$C$35,2,0) -> Serbia | D1023: 8 | F1023: 0.086 | G1023: 0
A1024: 5 | B1024: 34 | C1024: =VLOOKUP(B1024,id_region!$A$1:$C$35,2,0) -> Serbia | D1024: 9 | F1024: 0 | G1024: 0
A1025: 5 | B1025: 34 | C1025: =VLOOKUP(B1025,id_region!$A$1:$C$35,2,0) -> Serbia | D1025: 10 | F1025: 0 | G1025: 0
A1026: 5 | B1026: 34 | C1026: =VLOOKUP(B1026,id_region!$A$1:$C$35,2,0) -> Serbia | D1026: 13 | F1026: 0 | G1026: 0
... A1030: 5 | B1030: 34 | C1030: =VLOOKUP(B1030,id_region!$A$1:$C$35,2,0) -> Serbia | D1030: 11 | F1030: 0 | G1030: 0

Sheet investment_funding_per_tech
A1: product_name | B1: process_name | C1: Unit | D1: Reference Technology | E1: Y2022 | F1: Y2050 | G1: parametrization_type | H1: Comment
A2: Ammonia | B2: Ammonia SMR | C2: Euros / t production capacity | D2: Full cost | E2: 0 | F2: 0 | G2: linear | H2: no funding
A3: Steel, primary | B3: Blast furnace | C3: Euros / t production capacity | D3: Full cost | E3: 0 | F3: 0 | G3: linear | H3: no funding
A4: Methanol | B4: Methanol SMR | C4: Euros / t production capacity | D4: Full cost | E4: 0 | F4: 0 | G4: linear | H4: no funding
A5: Ethylene | B5: Steam cracking | C5: Euros / t production capacity | D5: Full cost | E5: 0 | F5: 0 | G5: linear | H5: no funding
A6: Ammonia | B6: Ammonia H2 | C6: Euros / t production capacity | D6: Full cost | E6: 0 | F6: 0 | G6: linear | H6: no funding
A7: Methanol | B7: Methanol H2 | C7: Euros / t production capacity | D7: Full cost | E7: 0 | F7: 0 | G7: linear | H7: no funding
A8: Ethylene | B8: Ethylene H2 | C8: Euros / t production capacity | D8: Full cost | E8: 0 | F8: 0 | G8: linear | H8: no funding
A9: Steel, primary | B9: Direct reduction NG | C9: Euros / t production capacity | D9: Full cost | E9: 0 | F9: 0 | G9: linear | H9: no funding
A10: Steel, primary | B10: Direct reduction H2 | C10: Euros / t production capacity | D10: Full cost | E10: 0 | F10: 0 | G10: linear | H10: no funding

Sheet co2_price_development
A1: id_scenario | B1: co2_variation | C1: co2_price_2022_in_euro_per_ton | D1: co2_price_2050_in_euro_per_ton | E1: parametrization
A2: 1 | B2: 250 | C2: 80 | D2: 250 | E2: linear
A3: 2 | B3: 250 | C3: 80 | D3: 250 | E3: linear
A4: 3 | B4: 250 | C4: 80 | D4: 250 | E4: linear
A5: 4 | B5: 250 | C5: 80 | D5: 250 | E5: linear
A6: 1 | B6: 300 | C6: 80 | D6: 300 | E6: linear
A7: 2 | B7: 300 | C7: 80 | D7: 300 | E7: linear
A8: 3 | B8: 300 | C8: 80 | D8: 300 | E8: linear
A9: 4 | B9: 300 | C9: 80 | D9: 300 | E9: linear
A10: 1 | B10: 350 | C10: 80 | D10: 350 | E10: linear
A11: 2 | B11: 350 | C11: 80 | D11: 350 | E11: linear
A12: 3 | B12: 350 | C12: 80 | D12: 350 | E12: linear
A13: 4 | B13: 350 | C13: 80 | D13: 350 | E13: linear
... A17: 4 | B17: 400 | C17: 80 | D17: 400 | E17: linear

Sheet hydrogen_sensitivity
A1: id_scenario | B1: id_region | C1: region_name | D1: id_energy_carrier | E1: energy_carrier_name | F1: unit | G1: cost_2022_in_euro_per_gj | H1: cost_2030_in_euro_per_gj | I1: cost_2050_in_euro_per_gj | J1: comment
A2: 1 | B2: 1 | C2: Austria | D2: 15 | E2: Hydrogen | F2: Euros/GJ | G2: 57 | H2: 40 | I2: 30 | J2: Sensitivity high H2-price
A3: 1 | B3: 2 | C3: Belgium | D3: 15 | E3: Hydrogen | F3: Euros/GJ | G3: 57 | H3: 40 | I3: 30 | J3: Sensitivity high H2-price
A4: 1 | B4: 3 | C4: Cyprus | D4: 15 | E4: Hydrogen | F4: Euros/GJ | G4: 57 | H4: 40 | I4: 30 | J4: Sensitivity high H2-price
A5: 1 | B5: 4 | C5: Czech_Republic | D5: 15 | E5: Hydrogen | F5: Euros/GJ | G5: 57 | H5: 40 | I5: 30 | J5: Sensitivity high H2-price
A6: 1 | B6: 5 | C6: Denmark | D6: 15 | E6: Hydrogen | F6: Euros/GJ | G6: 57 | H6: 40 | I6: 30 | J6: Sensitivity high H2-price
A7: 1 | B7: 6 | C7: Estonia | D7: 15 | E7: Hydrogen | F7: Euros/GJ | G7: 57 | H7: 40 | I7: 30 | J7: Sensitivity high H2-price
A8: 1 | B8: 7 | C8: Finland | D8: 15 | E8: Hydrogen | F8: Euros/GJ | G8: 57 | H8: 40 | I8: 30 | J8: Sensitivity high H2-price
A9: 1 | B9: 8 | C9: France | D9: 15 | E9: Hydrogen | F9: Euros/GJ | G9: 57 | H9: 40 | I9: 30 | J9: Sensitivity high H2-price
A10: 1 | B10: 9 | C10: Germany | D10: 15 | E10: Hydrogen | F10: Euros/GJ | G10: 57 | H10: 40 | I10: 30 | J10: Sensitivity high H2-price
A11: 1 | B11: 10 | C11: Greece | D11: 15 | E11: Hydrogen | F11: Euros/GJ | G11: 57 | H11: 40 | I11: 30 | J11: Sensitivity high H2-price
A12: 1 | B12: 11 | C12: Hungary | D12: 15 | E12: Hydrogen | F12: Euros/GJ | G12: 57 | H12: 40 | I12: 30 | J12: Sensitivity high H2-price
A13: 1 | B13: 12 | C13: Ireland | D13: 15 | E13: Hydrogen | F13: Euros/GJ | G13: 57 | H13: 40 | I13: 30 | J13: Sensitivity high H2-price
... A137: 4 | B137: 33 | C137: Iceland | D137: 15 | E137: Hydrogen | F137: Euros/GJ | G137: 27 | H137: 20 | I137: 15 | J137: Sensitivity low H2-price

Sheet efficiency_improvement_per_tech
A1: product_name | B1: process_name | C1: Unit | D1: Reference | E1: Y2022 | F1: Y2050 | G1: parametrization_type | H1: Comment
A2: Ammonia | B2: Ammonia SMR | C2: % | D2: efficiency 2022 | E2: 0 | F2: 0 | G2: linear | H2: no improvements
A3: Steel, primary | B3: Blast furnace | C3: % | D3: efficiency 2022 | E3: 0 | F3: 0 | G3: linear | H3: no improvements
A4: Methanol | B4: Methanol SMR | C4: % | D4: efficiency 2022 | E4: 0 | F4: 0 | G4: linear | H4: no improvements
A5: Ethylene | B5: Steam cracking | C5: % | D5: efficiency 2022 | E5: 0 | F5: 0 | G5: linear | H5: no improvements
A6: Ammonia | B6: Ammonia H2 | C6: % | D6: efficiency 2022 | E6: 0 | F6: 0 | G6: linear | H6: no improvements
A7: Methanol | B7: Methanol H2 | C7: % | D7: efficiency 2022 | E7: 0 | F7: 0 | G7: linear | H7: no improvements
A8: Ethylene | B8: Ethylene H2 | C8: % | D8: efficiency 2022 | E8: 0 | F8: 0 | G8: linear | H8: no improvements
A9: Steel, primary | B9: Direct reduction NG | C9: % | D9: efficiency 2022 | E9: 0 | F9: 0 | G9: linear | H9: no improvements
A10: Steel, primary | B10: Direct reduction H2 | C10: % | D10: efficiency 2022 | E10: 0 | F10: 0 | G10: linear | H10: no improvements

Sheet techdb_capex
A1: product_name | B1: process_name | C1: Unit | D1: Y2022 | E1: Y2030 | F1: Y2050 | G1: parametrization_type | H1: Comment
A2: Ammonia | B2: Ammonia SMR | C2: Euros / t production capacity | D2: 550 | E2: 550 | F2: 550 | G2: linear | H2: Source: See manuscript
A3: Steel, primary | B3: Blast furnace | C3: Euros / t production capacity | D3: 170 | E3: 170 | F3: 170 | G3: linear | H3: Source: See manuscript
A4: Methanol | B4: Methanol SMR | C4: Euros / t production capacity | D4: 590 | E4: 590 | F4: 590 | G4: linear | H4: Source: See manuscript
A5: Ethylene | B5: Steam cracking | C5: Euros / t production capacity | D5: 1700 | E5: 1700 | F5: 1743 | G5: linear | H5: Source: See manuscript
A6: Ammonia | B6: Ammonia H2 | C6: Euros / t production capacity | D6: 110 | E6: 110 | F6: 110 | G6: linear | H6: Source: See manuscript
A7: Methanol | B7: Methanol H2 | C7: Euros / t production capacity | D7: 300 | E7: 300 | F7: 300 | G7: linear | H7: Source: See manuscript
A8: Ethylene | B8: Ethylene H2 | C8: Euros / t production capacity | D8: 1000 | E8: 1000 | F8: 1000 | G8: linear | H8: Source: See manuscript
A9: Steel, primary | B9: Direct reduction NG | C9: Euros / t production capacity | D9: 795 | E9: 795 | F9: 795 | G9: linear | H9: Source: See manuscript
A10: Steel, primary | B10: Direct reduction H2 | C10: Euros / t production capacity | D10: 795 | E10: 795 | F10: 795 | G10: linear | H10: Source: See manuscript

Sheet techdb_opex
A1: product_name | B1: process_name | C1: unit | D1: Y2015 | E1: Y2030 | F1: Y2050 | G1: parametrization_type | H1: Comment
A2: Ammonia | B2: Ammonia SMR | C2: €/t | D2: 30 | E2: 30 | F2: 30 | G2: linear | H2: Source: see manuscript
A3: Steel, primary | B3: Blast furnace | C3: €/t | D3: 295 | E3: 295 | F3: 295 | G3: linear | H3: Source: see manuscript
A4: Methanol | B4: Methanol SMR | C4: €/t | D4: 21 | E4: 21 | F4: 21 | G4: linear | H4: Source: see manuscript
A5: Ethylene | B5: Steam cracking | C5: €/t | D5: 60 | E5: 60 | F5: 60 | G5: linear | H5: Source: see manuscript
A6: Ammonia | B6: Ammonia H2 | C6: €/t | D6: 40 | E6: 40 | F6: 40 | G6: linear | H6: Source: see manuscript
A7: Methanol | B7: Methanol H2 | C7: €/t | D7: 50 | E7: 50 | F7: 50 | G7: linear | H7: Source: see manuscript
A8: Ethylene | B8: Ethylene H2 | C8: €/t | D8: 25 | E8: 25 | F8: 25 | G8: linear | H8: Source: see manuscript
A9: Steel, primary | B9: Direct reduction NG | C9: €/t | D9: 340 | E9: 340 | F9: 340 | G9: linear | H9: Source: see manuscript
A10: Steel, primary | B10: Direct reduction H2 | C10: €/t | D10: 340 | E10: 340 | F10: 340 | G10: linear | H10: Source: see manuscript

Sheet techdb_energydemand
A1: product_name | B1: process_name | C1: unit | D1: fuel_demand | E1: steam_demand | F1: electricity_demand | G1: feedstock_demand | H1: comment
A2: Steel, primary | B2: Blast furnace | C2: GJ/t | D2: 16.7 | E2: 0.92 | F2: 1.1 | G2: 0 | H2: Source: see manuscript
A3: Ammonia | B3: Ammonia SMR | C3: GJ/t | D3: 9.4 | E3: -1.8 | F3: 3.2 | G3: 21.4 | H3: Source: see manuscript
A4: Ethylene | B4: Steam cracking | C4: GJ/t | D4: 33.9 | E4: 0 | F4: 1.56 | G4: 102.5 | H4: Source: see manuscript
A5: Methanol | B5: Methanol SMR | C5: GJ/t | D5: 12.1 | E5: -0.9 | F5: 0.5 | G5: 22.6 | H5: Source: see manuscript
A6: Ammonia | B6: Ammonia H2 | C6: GJ/t | D6: 0 | E6: -0.9 | F6: 4.8 | G6: 21.4 | H6: Source: see manuscript
A7: Methanol | B7: Methanol H2 | C7: GJ/t | D7: 0 | E7: 0.4 | F7: 0.8 | G7: 22.6 | H7: Source: see manuscript
A8: Ethylene | B8: Ethylene H2 | C8: GJ/t | D8: 0 | E8: 0.8 | F8: 0 | G8: 138.9 | H8: Source: see manuscript
A9: Steel, primary | B9: Direct reduction NG | C9: GJ/t | D9: 9 | E9: 0 | F9: 2.1 | G9: 0 | H9: Source: see manuscript
A10: Steel, primary | B10: Direct reduction H2 | C10: GJ/t | D10: 6.8 | E10: 0 | F10: 1.7 | G10: 0 | H10: Source: see manuscript

Sheet techdb_fuelshare
A1: product_name | B1: process_name | C1: Coal | D1: Natural gas | E1: Derived Gases | F1: Hydrogen
A2: Steel, primary | B2: Blast furnace | C2: 0.76 | D2: 0.07 | E2: 0.17 | F2: 0
A3: Ammonia | B3: Ammonia SMR | C3: 0 | D3: 1 | E3: 0 | F3: 0
A4: Ethylene | B4: Steam cracking | C4: 0 | D4: 1 | E4: 0 | F4: 0
A5: Methanol | B5: Methanol SMR | C5: 0 | D5: 1 | E5: 0 | F5: 0
A6: Steel, primary | B6: Direct reduction NG | C6: 0 | D6: 1 | E6: 0 | F6: 0
A7: Steel, primary | B7: Direct reduction H2 | C7: 0 | D7: 0 | E7: 0 | F7: 1

Sheet techdb_steamshare
A1: product_name | B1: process_name | C1: Coal | D1: Natural gas | E1: Derived Gases | F1: Hydrogen
A2: Steel, primary | B2: Blast furnace | C2: 0.76 | D2: 0.07 | E2: 0.17 | F2: 0
A3: Ammonia | B3: Ammonia SMR | C3: 0 | D3: 1 | E3: 0 | F3: 0
A4: Ethylene | B4: Steam cracking | C4: 0 | D4: 1 | E4: 0 | F4: 0
A5: Methanol | B5: Methanol SMR | C5: 0 | D5: 1 | E5: 0 | F5: 0
A6: Steel, primary | B6: Direct reduction NG | C6: 0 | D6: 1 | E6: 0 | F6: 0
A7: Steel, primary | B7: Direct reduction H2 | C7: 0 | D7: 0 | E7: 0 | F7: 1

Sheet techdb_feedstockshare
A1: product_name | B1: process_name | C1: Natural gas | D1: Hydrogen | E1: Naphtha
A2: Ammonia | B2: Ammonia SMR | C2: 1 | D2: 0 | E2: 0
A3: Ethylene | B3: Steam cracking | C3: 0 | D3: 0 | E3: 1
A4: Methanol | B4: Methanol SMR | C4: 1 | D4: 0 | E4: 0
A5: Ammonia | B5: Ammonia H2 | C5: 0 | D5: 1 | E5: 0
A6: Ethylene | B6: Methanol-to-HVC | C6: 0 | D6: 1 | E6: 0
A7: Methanol | B7: Methanol H2 | C7: 0 | D7: 1 | E7: 0

Sheet techdb_lifetime
A1: product_name | B1: process_name | C1: lifetime_in_years | D1: depreciation_period | E1: interest_rate
A2: Steel, primary | B2: Blast furnace | C2: 20 | D2: 20 | E2: 0.08
A3: Ammonia | B3: Ammonia SMR | C3: 25 | D3: 20 | E3: 0.08
A4: Ethylene | B4: Steam cracking | C4: 25 | D4: 20 | E4: 0.08
A5: Methanol | B5: Methanol SMR | C5: 25 | D5: 20 | E5: 0.08
A6: Ammonia | B6: Ammonia H2 | C6: 25 | D6: 20 | E6: 0.08
A7: Methanol | B7: Methanol H2 | C7: 25 | D7: 20 | E7: 0.08
A8: Ethylene | B8: Ethylene H2 | C8: 30 | D8: 20 | E8: 0.08
A9: Steel, primary | B9: Direct reduction NG | C9: 25 | D9: 20 | E9: 0.08
A10: Steel, primary | B10: Direct reduction H2 | C10: 25 | D10: 20 | E10: 0.08

Sheet id_region
A1: id | B1: name | C1: abbreviation
A2: 1 | B2: Austria | C2: AT
A3: 2 | B3: Belgium | C3: BE
A4: 3 | B4: Cyprus | C4: CY
A5: 4 | B5: Czech_Republic | C5: CZ
A6: 5 | B6: Denmark | C6: DK
A7: 6 | B7: Estonia | C7: EE
A8: 7 | B8: Finland | C8: FI
A9: 8 | B9: France | C9: FR
A10: 9 | B10: Germany | C10: DE
A11: 10 | B11: Greece | C11: EL
A12: 11 | B12: Hungary | C12: HU
A13: 12 | B13: Ireland | C13: IE
... A35: 34 | B35: Serbia | C35: RS

Sheet id_energy_carrier
A1: id | B1: name
A2: 1 | B2: Electricity
A3: 3 | B3: Coal
A4: 4 | B4: Natural gas
A5: 11 | B5: Derived Gases
A6: 14 | B6: Naphtha
A7: 15 | B7: Hydrogen
